richdaddy_sdk/__init__.py
richdaddy_sdk/aiorichdaddy/__init__.py
richdaddy_sdk/aiorichdaddy/client.py
richdaddy_sdk/aiorichdaddy/methods.py
richdaddy_sdk/syncrichdaddy/__init__.py
richdaddy_sdk/syncrichdaddy/client.py
richdaddy_sdk/syncrichdaddy/methods.py
richdaddy_sdk-1.0.0.dist-info/LICENSE
richdaddy_sdk-1.0.0.dist-info/METADATA
richdaddy_sdk-1.0.0.dist-info/WHEEL
richdaddy_sdk-1.0.0.dist-info/top_level.txt
richdaddy_sdk-1.0.0.dist-info/RECORD
