Metadata-Version: 2.1
Name: richdaddy-sdk
Version: 1.0.0
Summary: UNKNOWN
Home-page: https://github.com/old-pinky/RichDaddy_SDK
License: UNKNOWN
Platform: UNKNOWN
License-File: LICENSE
Requires-Dist: loguru
Requires-Dist: asyncio
Requires-Dist: aiohttp
